setup.py
funker/__init__.py
funker/call.py
funker/handle.py
funker.egg-info/PKG-INFO
funker.egg-info/SOURCES.txt
funker.egg-info/dependency_links.txt
funker.egg-info/requires.txt
funker.egg-info/top_level.txt