Metadata-Version: 1.0
Name: funker
Version: 0.0.1
Summary: Functions as Docker containers
Home-page: https://github.com/bfirsh/funker-python
Author: UNKNOWN
Author-email: UNKNOWN
License: UNKNOWN
Platform: UNKNOWN
